sublime/__init__.py
sublime/__version__.py
sublime/api.py
sublime/error.py
sublime/util.py
sublime/cli/__init__.py
sublime/cli/decorator.py
sublime/cli/formatter.py
sublime/cli/outlookmsgfile_helper.py
sublime/cli/subcommand.py
sublime/cli/templates/analyze.txt.j2
sublime/cli/templates/analyze_multi.txt.j2
sublime/cli/templates/feedback_result.txt.j2
sublime/cli/templates/macros.txt.j2
sublime/cli/templates/me_result.txt.j2
sublime/cli/templates/message_data_model.txt.j2
sublime_cli-0.0.31.dist-info/LICENSE
sublime_cli-0.0.31.dist-info/METADATA
sublime_cli-0.0.31.dist-info/WHEEL
sublime_cli-0.0.31.dist-info/entry_points.txt
sublime_cli-0.0.31.dist-info/top_level.txt
sublime_cli-0.0.31.dist-info/RECORD
