Metadata-Version: 2.1
Name: sublime-cli
Version: 0.0.31
Summary: Abstraction to interact with the Sublime API.
Home-page: https://sublimesecurity.com/
Download-URL: https://github.com/sublime-security/sublime-cli
Author: Sublime Security
Author-email: hello@sublimesecurity.com
License: MIT
Keywords: security,phishing,analysts,soc,threat intelligence,security-automation,email security
Classifier: Development Status :: 4 - Beta
Classifier: Intended Audience :: Developers
Classifier: License :: OSI Approved :: MIT License
Classifier: Natural Language :: English
Classifier: Programming Language :: Python
Classifier: Programming Language :: Python :: 3.7
Classifier: Topic :: Software Development :: Libraries
License-File: LICENSE
Requires-Dist: Click >=7.0
Requires-Dist: ansimarkup
Requires-Dist: cachetools
Requires-Dist: click-default-group
Requires-Dist: click-repl
Requires-Dist: compoundfiles
Requires-Dist: compressed-rtf
Requires-Dist: gron
Requires-Dist: halo
Requires-Dist: jinja2
Requires-Dist: more-itertools
Requires-Dist: msg-parser
Requires-Dist: olefile
Requires-Dist: pyyaml
Requires-Dist: requests
Requires-Dist: six
Requires-Dist: structlog
Requires-Dist: websockets
